hotpayments/__init__.py
hotpayments/base_service.py
hotpayments/client.py
hotpayments/exceptions.py
hotpayments/types.py
hotpayments/services/__init__.py
hotpayments/services/customers.py
hotpayments/services/subscription_plans.py
hotpayments/services/subscriptions.py
hotpayments/services/transactions.py
hotpayments_python_sdk-1.0.0.dist-info/licenses/LICENSE
hotpayments_python_sdk-1.0.0.dist-info/METADATA
hotpayments_python_sdk-1.0.0.dist-info/WHEEL
hotpayments_python_sdk-1.0.0.dist-info/top_level.txt
hotpayments_python_sdk-1.0.0.dist-info/RECORD
