Metadata-Version: 2.4
Name: hotpayments-python-sdk
Version: 1.0.0
Summary: Python SDK for HotPayments API - Handle payments, subscriptions, PIX transactions with a clean, async-ready interface.
Author-email: HotPayments <contato@hotpayments.net>
License: MIT
Project-URL: Homepage, https://github.com/hotpayments/python-sdk
Project-URL: Repository, https://github.com/hotpayments/python-sdk.git
Project-URL: Documentation, https://github.com/hotpayments/python-sdk
Project-URL: Bug Tracker, https://github.com/hotpayments/python-sdk/issues
Keywords: payments,pix,subscriptions,hotpayments,sdk
Classifier: Development Status :: 5 - Production/Stable
Classifier: Intended Audience :: Developers
Classifier: License :: OSI Approved :: MIT License
Classifier: Operating System :: OS Independent
Classifier: Programming Language :: Python :: 3
Classifier: Programming Language :: Python :: 3.8
Classifier: Programming Language :: Python :: 3.9
Classifier: Programming Language :: Python :: 3.10
Classifier: Programming Language :: Python :: 3.11
Classifier: Programming Language :: Python :: 3.12
Classifier: Topic :: Software Development :: Libraries :: Python Modules
Classifier: Topic :: Office/Business :: Financial
Requires-Python: >=3.8
License-File: LICENSE
Requires-Dist: httpx>=0.24.0
Requires-Dist: pydantic>=2.0.0
Provides-Extra: dev
Requires-Dist: pytest>=7.0.0; extra == "dev"
Requires-Dist: pytest-asyncio>=0.21.0; extra == "dev"
Requires-Dist: pytest-httpx>=0.21.0; extra == "dev"
Requires-Dist: black>=23.0.0; extra == "dev"
Requires-Dist: isort>=5.12.0; extra == "dev"
Requires-Dist: mypy>=1.0.0; extra == "dev"
Requires-Dist: flake8>=6.0.0; extra == "dev"
Dynamic: license-file
